flash_fuzzy-0.1.0.dist-info/METADATA
flash_fuzzy-0.1.0.dist-info/WHEEL
flash_fuzzy/__init__.py
flash_fuzzy/__init__.pyi
flash_fuzzy/flash_fuzzy.cp313-win_amd64.pyd
flash_fuzzy-0.1.0.dist-info/RECORD
