Metadata-Version: 2.4
Name: flash-fuzzy
Version: 0.1.0
Classifier: Development Status :: 4 - Beta
Classifier: Intended Audience :: Developers
Classifier: License :: OSI Approved :: MIT License
Classifier: Operating System :: OS Independent
Classifier: Programming Language :: Python :: 3
Classifier: Programming Language :: Python :: 3.8
Classifier: Programming Language :: Python :: 3.9
Classifier: Programming Language :: Python :: 3.10
Classifier: Programming Language :: Python :: 3.11
Classifier: Programming Language :: Python :: 3.12
Classifier: Programming Language :: Python :: Implementation :: CPython
Classifier: Programming Language :: Rust
Classifier: Topic :: Software Development :: Libraries :: Python Modules
Classifier: Topic :: Text Processing :: Indexing
Classifier: Topic :: Text Processing :: Linguistic
Classifier: Typing :: Typed
Summary: High-performance fuzzy search engine using Bitap algorithm with bloom filter pre-filtering. Powered by Rust for blazing fast performance.
Keywords: fuzzy,search,fast,rust,bitap,fuzzy-search,text-search,approximate-matching
Author-email: RafaCalRob <contact@bdovenbird.com>
Maintainer-email: BDOvenbird Team <contact@bdovenbird.com>
License: MIT
Requires-Python: >=3.8
Project-URL: Homepage, https://github.com/RafaCalRob/FlashFuzzy
Project-URL: Documentation, https://github.com/RafaCalRob/FlashFuzzy#readme
Project-URL: Repository, https://github.com/RafaCalRob/FlashFuzzy
Project-URL: Issues, https://github.com/RafaCalRob/FlashFuzzy/issues
Project-URL: Changelog, https://github.com/RafaCalRob/FlashFuzzy/blob/main/CHANGELOG.md
